wattleflow/api/__init__.py
wattleflow/api/endpoints.py
wattleflow/api/endpoints/__init__.py
wattleflow/api/endpoints/model/youtube.py
wattleflow/audit/__init__.py
wattleflow/blackboards/__init__.py
wattleflow/concrete/__init__.py
wattleflow/concrete/_version.py
wattleflow/concrete/blackboard.py
wattleflow/concrete/connection.py
wattleflow/concrete/document.py
wattleflow/concrete/driver.py
wattleflow/concrete/exception.py
wattleflow/concrete/logger.py
wattleflow/concrete/manager.py
wattleflow/concrete/memento.py
wattleflow/concrete/orchestrator.py
wattleflow/concrete/pipeline.py
wattleflow/concrete/processor.py
wattleflow/concrete/repository.py
wattleflow/concrete/scheduler.py
wattleflow/concrete/strategy.py
wattleflow/connections/__init__.py
wattleflow/connections/postgres.py
wattleflow/connections/sftp_paramiko.py
wattleflow/constants/__init__.py
wattleflow/constants/audit.py
wattleflow/constants/enums.py
wattleflow/constants/errors.py
wattleflow/constants/keys.py
wattleflow/core/__init__.py
wattleflow/core/_version.py
wattleflow/core/behavioral.py
wattleflow/core/concurrent.py
wattleflow/core/creational.py
wattleflow/core/framework.py
wattleflow/core/structural.py
wattleflow/core/transactional.py
wattleflow/decorators/__init__.py
wattleflow/decorators/file.py
wattleflow/decorators/preset.py
wattleflow/decorators/pspf.py
wattleflow/doc/wattleflow.png
wattleflow/documents/__init__.py
wattleflow/documents/dataframe.py
wattleflow/documents/dictionary.py
wattleflow/documents/file.py
wattleflow/documents/item.py
wattleflow/documents/rdf.py
wattleflow/documents/wattle.py
wattleflow/drivers/__init__.py
wattleflow/drivers/local_file_system_driver.py
wattleflow/helpers/__init__.py
wattleflow/helpers/attribute.py
wattleflow/helpers/audit.py
wattleflow/helpers/collections.py
wattleflow/helpers/config.py
wattleflow/helpers/dictionaries.py
wattleflow/helpers/functions.py
wattleflow/helpers/generators.py
wattleflow/helpers/handlers.py
wattleflow/helpers/localmodels.py
wattleflow_workflow-0.0.0.58.dist-info/licenses/LICENSE
wattleflow_workflow-0.0.0.58.dist-info/METADATA
wattleflow_workflow-0.0.0.58.dist-info/WHEEL
wattleflow_workflow-0.0.0.58.dist-info/top_level.txt
wattleflow_workflow-0.0.0.58.dist-info/RECORD
