Metadata-Version: 2.4
Name: wattleflow-workflow
Version: 0.0.0.58
Summary: Wattleflow Workflow - Data engineering framework.
Home-page: https://github.com/wattleflow/workflow.git
Author: WattleFlow
Author-email: wattleflow <wattleflow@outlook.com>
License-Expression: Apache-2.0
Project-URL: homepage, https://github.com/wattleflow/workflow.git
Project-URL: repository, https://github.com/wattleflow/workflow.git
Project-URL: documentation, https://github.com/wattleflow/workflow.git
Keywords: wattleflow,workflow,data,engineering,framework,python,library,software engineering
Classifier: Development Status :: 5 - Production/Stable
Classifier: Programming Language :: Python :: 3.9
Classifier: Programming Language :: Python :: 3.10
Classifier: Programming Language :: Python :: 3.11
Classifier: Programming Language :: Python :: 3.12
Classifier: Programming Language :: Python :: 3.13
Classifier: Operating System :: OS Independent
Classifier: Intended Audience :: Developers
Classifier: Topic :: Software Development :: Libraries
Classifier: Topic :: Software Development :: Libraries :: Python Modules
Requires-Python: >=3.9
License-File: LICENSE
Requires-Dist: cryptography
Requires-Dist: wattleflow>=0.0.0.25
Dynamic: author
Dynamic: home-page
Dynamic: license-file
Dynamic: requires-python
